[{"model": "portfolio.photocategory", "pk": 1, "fields": {"title": "Story I"}}, {"model": "portfolio.photocategory", "pk": 2, "fields": {"title": "Story II"}}, {"model": "portfolio.photocategory", "pk": 3, "fields": {"title": "Story III"}}, {"model": "portfolio.photo", "pk": 1, "fields": {"title": "01_story_1.jpg", "images": "portfolio/images/01_story_1.jpg", "description": null, "ordering": 1, "category": 1}}, {"model": "portfolio.photo", "pk": 2, "fields": {"title": "02_story_1.jpg", "images": "portfolio/images/02_story_1.jpg", "description": null, "ordering": 2, "category": 1}}, {"model": "portfolio.photo", "pk": 3, "fields": {"title": "03_PHG_3864_story_1.jpg", "images": "portfolio/images/03_PHG_3864_story_1.jpg", "description": null, "ordering": 3, "category": 1}}, {"model": "portfolio.photo", "pk": 4, "fields": {"title": "04_PHG_3770_story_1.jpg", "images": "portfolio/images/04_PHG_3770_story_1.jpg", "description": null, "ordering": 4, "category": 1}}, {"model": "portfolio.photo", "pk": 5, "fields": {"title": "05_PHG_4241_story_1.jpg", "images": "portfolio/images/05_PHG_4241_story_1.jpg", "description": null, "ordering": 5, "category": 1}}, {"model": "portfolio.photo", "pk": 6, "fields": {"title": "06_PHG_3490_story_1.jpg", "images": "portfolio/images/06_PHG_3490_story_1.jpg", "description": null, "ordering": 6, "category": 1}}, {"model": "portfolio.photo", "pk": 7, "fields": {"title": "07_PHG_3369_story_1.jpg", "images": "portfolio/images/07_PHG_3369_story_1.jpg", "description": null, "ordering": 7, "category": 1}}, {"model": "portfolio.photo", "pk": 8, "fields": {"title": "08_PHG_4022_story_1.jpg", "images": "portfolio/images/08_PHG_4022_story_1.jpg", "description": null, "ordering": 8, "category": 1}}, {"model": "portfolio.photo", "pk": 9, "fields": {"title": "09_PHG_4120_story_1.jpg", "images": "portfolio/images/09_PHG_4120_story_1.jpg", "description": null, "ordering": 9, "category": 1}}, {"model": "portfolio.photo", "pk": 10, "fields": {"title": "10_PHG_3982_story_1.jpg", "images": "portfolio/images/10_PHG_3982_story_1.jpg", "description": null, "ordering": 10, "category": 1}}, {"model": "portfolio.photo", "pk": 11, "fields": {"title": "11_PHG_4587_story_1.jpg", "images": "portfolio/images/11_PHG_4587_story_1.jpg", "description": null, "ordering": 11, "category": 1}}, {"model": "portfolio.photo", "pk": 12, "fields": {"title": "12_PHG_4274_story_1.jpg", "images": "portfolio/images/12_PHG_4274_story_1.jpg", "description": null, "ordering": 12, "category": 1}}, {"model": "portfolio.photo", "pk": 13, "fields": {"title": "13_PHG_4228_story_1.jpg", "images": "portfolio/images/13_PHG_4228_story_1.jpg", "description": null, "ordering": 13, "category": 1}}, {"model": "portfolio.photo", "pk": 14, "fields": {"title": "14_PHG_3942_story_1.jpg", "images": "portfolio/images/14_PHG_3942_story_1.jpg", "description": null, "ordering": 14, "category": 1}}, {"model": "portfolio.photo", "pk": 15, "fields": {"title": "15_PHG_4299_story_1.jpg", "images": "portfolio/images/15_PHG_4299_story_1.jpg", "description": null, "ordering": 15, "category": 1}}, {"model": "portfolio.photo", "pk": 16, "fields": {"title": "16_PHG_4487_story_1.jpg", "images": "portfolio/images/16_PHG_4487_story_1.jpg", "description": null, "ordering": 16, "category": 1}}, {"model": "portfolio.photo", "pk": 17, "fields": {"title": "01_story_2.jpg", "images": "portfolio/images/01_story_2.jpg", "description": null, "ordering": 1, "category": 2}}, {"model": "portfolio.photo", "pk": 18, "fields": {"title": "02_story_2.jpg", "images": "portfolio/images/02_story_2.jpg", "description": null, "ordering": 2, "category": 2}}, {"model": "portfolio.photo", "pk": 19, "fields": {"title": "03_LinhPh-5852-2_story_2.jpg", "images": "portfolio/images/03_LinhPh-5852-2_story_2.jpg", "description": null, "ordering": 3, "category": 2}}, {"model": "portfolio.photo", "pk": 20, "fields": {"title": "03_story_2.jpg", "images": "portfolio/images/03_story_2.jpg", "description": null, "ordering": 4, "category": 2}}, {"model": "portfolio.photo", "pk": 21, "fields": {"title": "04_story_2.jpg", "images": "portfolio/images/04_story_2.jpg", "description": null, "ordering": 5, "category": 2}}, {"model": "portfolio.photo", "pk": 22, "fields": {"title": "05_LinhPh-8414_story_2.jpg", "images": "portfolio/images/05_LinhPh-8414_story_2.jpg", "description": null, "ordering": 6, "category": 2}}, {"model": "portfolio.photo", "pk": 23, "fields": {"title": "06_LinhPh-8517_story_2.jpg", "images": "portfolio/images/06_LinhPh-8517_story_2.jpg", "description": null, "ordering": 7, "category": 2}}, {"model": "portfolio.photo", "pk": 24, "fields": {"title": "07_story_2.jpg", "images": "portfolio/images/07_story_2.jpg", "description": null, "ordering": 8, "category": 2}}, {"model": "portfolio.photo", "pk": 25, "fields": {"title": "08_LinhPh-6015_story_2.jpg", "images": "portfolio/images/08_LinhPh-6015_story_2.jpg", "description": null, "ordering": 9, "category": 2}}, {"model": "portfolio.photo", "pk": 26, "fields": {"title": "09_LinhPh-8532_story_2.jpg", "images": "portfolio/images/09_LinhPh-8532_story_2.jpg", "description": null, "ordering": 10, "category": 2}}, {"model": "portfolio.photo", "pk": 27, "fields": {"title": "10_LinhPh-8579_story_2.jpg", "images": "portfolio/images/10_LinhPh-8579_story_2.jpg", "description": null, "ordering": 11, "category": 2}}, {"model": "portfolio.photo", "pk": 28, "fields": {"title": "11_LinhPh-7627_story_2.jpg", "images": "portfolio/images/11_LinhPh-7627_story_2.jpg", "description": null, "ordering": 12, "category": 2}}, {"model": "portfolio.photo", "pk": 29, "fields": {"title": "12_LinhPh-7671_story_2.jpg", "images": "portfolio/images/12_LinhPh-7671_story_2.jpg", "description": null, "ordering": 13, "category": 2}}, {"model": "portfolio.photo", "pk": 30, "fields": {"title": "13_LinhPh-9548_story_2.jpg", "images": "portfolio/images/13_LinhPh-9548_story_2.jpg", "description": null, "ordering": 14, "category": 2}}, {"model": "portfolio.photo", "pk": 31, "fields": {"title": "14_PHG_3368newedit_story_2.jpg", "images": "portfolio/images/14_PHG_3368newedit_story_2.jpg", "description": null, "ordering": 15, "category": 2}}, {"model": "portfolio.photo", "pk": 32, "fields": {"title": "15_LinhPh-8572_story_2.jpg", "images": "portfolio/images/15_LinhPh-8572_story_2.jpg", "description": null, "ordering": 16, "category": 2}}, {"model": "portfolio.photo", "pk": 33, "fields": {"title": "16_LinhPh-9655_story_2.jpg", "images": "portfolio/images/16_LinhPh-9655_story_2.jpg", "description": null, "ordering": 17, "category": 2}}, {"model": "portfolio.photo", "pk": 34, "fields": {"title": "17_PHG_1669.1_story_2.jpg", "images": "portfolio/images/17_PHG_1669.1_story_2.jpg", "description": null, "ordering": 18, "category": 2}}, {"model": "portfolio.photo", "pk": 35, "fields": {"title": "18_PHG_3471newedit_story_2.jpg", "images": "portfolio/images/18_PHG_3471newedit_story_2.jpg", "description": null, "ordering": 19, "category": 2}}, {"model": "portfolio.photo", "pk": 36, "fields": {"title": "19_LinhPh-9668_story_2.jpg", "images": "portfolio/images/19_LinhPh-9668_story_2.jpg", "description": null, "ordering": 20, "category": 2}}, {"model": "portfolio.photo", "pk": 37, "fields": {"title": "20_LinhPh-9675_story_2.jpg", "images": "portfolio/images/20_LinhPh-9675_story_2.jpg", "description": null, "ordering": 21, "category": 2}}, {"model": "portfolio.photo", "pk": 38, "fields": {"title": "21_PHG_3981_story_2.jpg", "images": "portfolio/images/21_PHG_3981_story_2.jpg", "description": null, "ordering": 22, "category": 2}}, {"model": "portfolio.photo", "pk": 39, "fields": {"title": "22_PHG_1661.1_story_2.jpg", "images": "portfolio/images/22_PHG_1661.1_story_2.jpg", "description": null, "ordering": 23, "category": 2}}, {"model": "portfolio.photo", "pk": 40, "fields": {"title": "23_PHG_3010_story_2.jpg", "images": "portfolio/images/23_PHG_3010_story_2.jpg", "description": null, "ordering": 24, "category": 2}}, {"model": "portfolio.photo", "pk": 41, "fields": {"title": "24_PHG_3431newedit_story_2.jpg", "images": "portfolio/images/24_PHG_3431newedit_story_2.jpg", "description": null, "ordering": 25, "category": 2}}, {"model": "portfolio.photo", "pk": 42, "fields": {"title": "25_PHG_7920-2_story_2.jpg", "images": "portfolio/images/25_PHG_7920-2_story_2.jpg", "description": null, "ordering": 26, "category": 2}}, {"model": "portfolio.photo", "pk": 43, "fields": {"title": "26_PHG_8118-3_story_2.jpg", "images": "portfolio/images/26_PHG_8118-3_story_2.jpg", "description": null, "ordering": 27, "category": 2}}, {"model": "portfolio.photo", "pk": 44, "fields": {"title": "27_PHG_8132-4_story_2.jpg", "images": "portfolio/images/27_PHG_8132-4_story_2.jpg", "description": null, "ordering": 28, "category": 2}}, {"model": "portfolio.photo", "pk": 45, "fields": {"title": "28_PHG_8299-5_story_2.jpg", "images": "portfolio/images/28_PHG_8299-5_story_2.jpg", "description": null, "ordering": 29, "category": 2}}, {"model": "portfolio.photo", "pk": 46, "fields": {"title": "29_PHG_9708_story_2.jpg", "images": "portfolio/images/29_PHG_9708_story_2.jpg", "description": null, "ordering": 30, "category": 2}}, {"model": "portfolio.photo", "pk": 47, "fields": {"title": "30_PHG_9755_story_2.jpg", "images": "portfolio/images/30_PHG_9755_story_2.jpg", "description": null, "ordering": 31, "category": 2}}, {"model": "portfolio.photo", "pk": 48, "fields": {"title": "31_PHG_9900_story_2.jpg", "images": "portfolio/images/31_PHG_9900_story_2.jpg", "description": null, "ordering": 32, "category": 2}}, {"model": "portfolio.photo", "pk": 49, "fields": {"title": "32_PHG_9968_story_2.jpg", "images": "portfolio/images/32_PHG_9968_story_2.jpg", "description": null, "ordering": 33, "category": 2}}, {"model": "portfolio.photo", "pk": 50, "fields": {"title": "01_story_3.jpg", "images": "portfolio/images/01_story_3.jpg", "description": null, "ordering": 1, "category": 3}}, {"model": "portfolio.photo", "pk": 51, "fields": {"title": "02_story_3.jpg", "images": "portfolio/images/02_story_3.jpg", "description": null, "ordering": 2, "category": 3}}, {"model": "portfolio.photo", "pk": 52, "fields": {"title": "03_story_3.jpg", "images": "portfolio/images/03_story_3.jpg", "description": null, "ordering": 3, "category": 3}}, {"model": "portfolio.photo", "pk": 53, "fields": {"title": "04_story_3.jpg", "images": "portfolio/images/04_story_3.jpg", "description": null, "ordering": 4, "category": 3}}, {"model": "portfolio.photo", "pk": 54, "fields": {"title": "05_LinhPh-0041_story_3.jpg", "images": "portfolio/images/05_LinhPh-0041_story_3.jpg", "description": null, "ordering": 5, "category": 3}}, {"model": "portfolio.photo", "pk": 55, "fields": {"title": "06_story_3.jpg", "images": "portfolio/images/06_story_3.jpg", "description": null, "ordering": 6, "category": 3}}, {"model": "portfolio.photo", "pk": 56, "fields": {"title": "07_story_3.jpg", "images": "portfolio/images/07_story_3.jpg", "description": null, "ordering": 7, "category": 3}}, {"model": "portfolio.photo", "pk": 57, "fields": {"title": "08_LinhPh-0061_story_3.jpg", "images": "portfolio/images/08_LinhPh-0061_story_3.jpg", "description": null, "ordering": 8, "category": 3}}, {"model": "portfolio.photo", "pk": 58, "fields": {"title": "09_LinhPh-4278_story_3.jpg", "images": "portfolio/images/09_LinhPh-4278_story_3.jpg", "description": null, "ordering": 9, "category": 3}}, {"model": "portfolio.photo", "pk": 59, "fields": {"title": "10_LinhPh-6260_story_3.jpg", "images": "portfolio/images/10_LinhPh-6260_story_3.jpg", "description": null, "ordering": 10, "category": 3}}, {"model": "portfolio.photo", "pk": 60, "fields": {"title": "11_LinhPh-6411_story_3.jpg", "images": "portfolio/images/11_LinhPh-6411_story_3.jpg", "description": null, "ordering": 11, "category": 3}}, {"model": "portfolio.photo", "pk": 61, "fields": {"title": "12_LinhPh-4392_story_3.jpg", "images": "portfolio/images/12_LinhPh-4392_story_3.jpg", "description": null, "ordering": 12, "category": 3}}, {"model": "portfolio.photo", "pk": 62, "fields": {"title": "13_LinhPh-6375_story_3.jpg", "images": "portfolio/images/13_LinhPh-6375_story_3.jpg", "description": null, "ordering": 13, "category": 3}}, {"model": "portfolio.photo", "pk": 63, "fields": {"title": "14_LinhPh-6507_story_3.jpg", "images": "portfolio/images/14_LinhPh-6507_story_3.jpg", "description": null, "ordering": 14, "category": 3}}, {"model": "portfolio.photo", "pk": 64, "fields": {"title": "15_LinhPh-6520_story_3.jpg", "images": "portfolio/images/15_LinhPh-6520_story_3.jpg", "description": null, "ordering": 15, "category": 3}}, {"model": "portfolio.photo", "pk": 65, "fields": {"title": "16_LinhPh-6402_story_3.jpg", "images": "portfolio/images/16_LinhPh-6402_story_3.jpg", "description": null, "ordering": 16, "category": 3}}, {"model": "portfolio.photo", "pk": 66, "fields": {"title": "17_LinhPh-6600_story_3.jpg", "images": "portfolio/images/17_LinhPh-6600_story_3.jpg", "description": null, "ordering": 17, "category": 3}}, {"model": "portfolio.photo", "pk": 67, "fields": {"title": "18_LinhPh-6555-2_story_3.jpg", "images": "portfolio/images/18_LinhPh-6555-2_story_3.jpg", "description": null, "ordering": 18, "category": 3}}, {"model": "portfolio.photo", "pk": 68, "fields": {"title": "19_LinhPh-6556_story_3.jpg", "images": "portfolio/images/19_LinhPh-6556_story_3.jpg", "description": null, "ordering": 19, "category": 3}}, {"model": "portfolio.photo", "pk": 69, "fields": {"title": "20_LinhPh-6633_story_3.jpg", "images": "portfolio/images/20_LinhPh-6633_story_3.jpg", "description": null, "ordering": 20, "category": 3}}, {"model": "portfolio.photo", "pk": 70, "fields": {"title": "21_LinhPh-6660_story_3.jpg", "images": "portfolio/images/21_LinhPh-6660_story_3.jpg", "description": null, "ordering": 21, "category": 3}}, {"model": "portfolio.photo", "pk": 71, "fields": {"title": "22_LinhPh-6603_story_3.jpg", "images": "portfolio/images/22_LinhPh-6603_story_3.jpg", "description": null, "ordering": 22, "category": 3}}, {"model": "portfolio.photo", "pk": 72, "fields": {"title": "23_LinhPh-6670_story_3.jpg", "images": "portfolio/images/23_LinhPh-6670_story_3.jpg", "description": null, "ordering": 23, "category": 3}}, {"model": "portfolio.photo", "pk": 73, "fields": {"title": "24_LinhPh-6765_story_3.jpg", "images": "portfolio/images/24_LinhPh-6765_story_3.jpg", "description": null, "ordering": 24, "category": 3}}, {"model": "portfolio.photo", "pk": 74, "fields": {"title": "25_LinhPh-6855_story_3.jpg", "images": "portfolio/images/25_LinhPh-6855_story_3.jpg", "description": null, "ordering": 25, "category": 3}}, {"model": "portfolio.photo", "pk": 75, "fields": {"title": "26_LinhPh-7017_story_3.jpg", "images": "portfolio/images/26_LinhPh-7017_story_3.jpg", "description": null, "ordering": 26, "category": 3}}, {"model": "portfolio.photo", "pk": 76, "fields": {"title": "27_LinhPh-7418_story_3.jpg", "images": "portfolio/images/27_LinhPh-7418_story_3.jpg", "description": null, "ordering": 27, "category": 3}}, {"model": "portfolio.photo", "pk": 77, "fields": {"title": "28_LinhPh-6952_story_3.jpg", "images": "portfolio/images/28_LinhPh-6952_story_3.jpg", "description": null, "ordering": 28, "category": 3}}, {"model": "portfolio.photo", "pk": 78, "fields": {"title": "29_LinhPh-6971_story_3.jpg", "images": "portfolio/images/29_LinhPh-6971_story_3.jpg", "description": null, "ordering": 29, "category": 3}}, {"model": "portfolio.photo", "pk": 79, "fields": {"title": "30_LinhPh-7530_story_3.jpg", "images": "portfolio/images/30_LinhPh-7530_story_3.jpg", "description": null, "ordering": 30, "category": 3}}, {"model": "portfolio.photo", "pk": 80, "fields": {"title": "31_LinhPh-7761_story_3.jpg", "images": "portfolio/images/31_LinhPh-7761_story_3.jpg", "description": null, "ordering": 31, "category": 3}}, {"model": "portfolio.photo", "pk": 81, "fields": {"title": "32_LinhPh-7180_story_3.jpg", "images": "portfolio/images/32_LinhPh-7180_story_3.jpg", "description": null, "ordering": 32, "category": 3}}, {"model": "portfolio.photo", "pk": 82, "fields": {"title": "33_LinhPh-7212_story_3.jpg", "images": "portfolio/images/33_LinhPh-7212_story_3.jpg", "description": null, "ordering": 33, "category": 3}}, {"model": "portfolio.photo", "pk": 83, "fields": {"title": "34_LinhPh-7937_story_3.jpg", "images": "portfolio/images/34_LinhPh-7937_story_3.jpg", "description": null, "ordering": 34, "category": 3}}, {"model": "portfolio.photo", "pk": 84, "fields": {"title": "35_LinhPh-7961-2_story_3.jpg", "images": "portfolio/images/35_LinhPh-7961-2_story_3.jpg", "description": null, "ordering": 35, "category": 3}}, {"model": "portfolio.photo", "pk": 85, "fields": {"title": "36_LinhPh-7290_story_3.jpg", "images": "portfolio/images/36_LinhPh-7290_story_3.jpg", "description": null, "ordering": 36, "category": 3}}, {"model": "portfolio.photo", "pk": 86, "fields": {"title": "37_LinhPh-7355_story_3.jpg", "images": "portfolio/images/37_LinhPh-7355_story_3.jpg", "description": null, "ordering": 37, "category": 3}}, {"model": "portfolio.photo", "pk": 87, "fields": {"title": "38_LinhPh-8091_story_3.jpg", "images": "portfolio/images/38_LinhPh-8091_story_3.jpg", "description": null, "ordering": 38, "category": 3}}, {"model": "portfolio.photo", "pk": 88, "fields": {"title": "39_LinhPh-8236_story_3.jpg", "images": "portfolio/images/39_LinhPh-8236_story_3.jpg", "description": null, "ordering": 39, "category": 3}}, {"model": "portfolio.photo", "pk": 89, "fields": {"title": "40_LinhPh-7448_story_3.jpg", "images": "portfolio/images/40_LinhPh-7448_story_3.jpg", "description": null, "ordering": 40, "category": 3}}, {"model": "portfolio.photo", "pk": 90, "fields": {"title": "41_LinhPh-7462_story_3.jpg", "images": "portfolio/images/41_LinhPh-7462_story_3.jpg", "description": null, "ordering": 41, "category": 3}}, {"model": "portfolio.photo", "pk": 91, "fields": {"title": "42_LinhPh-8385_story_3.jpg", "images": "portfolio/images/42_LinhPh-8385_story_3.jpg", "description": null, "ordering": 42, "category": 3}}, {"model": "portfolio.photo", "pk": 92, "fields": {"title": "43_LinhPh-8416_story_3.jpg", "images": "portfolio/images/43_LinhPh-8416_story_3.jpg", "description": null, "ordering": 43, "category": 3}}, {"model": "portfolio.photo", "pk": 93, "fields": {"title": "44_LinhPh-7529_story_3.jpg", "images": "portfolio/images/44_LinhPh-7529_story_3.jpg", "description": null, "ordering": 44, "category": 3}}, {"model": "portfolio.photo", "pk": 94, "fields": {"title": "45_LinhPh-7623_story_3.jpg", "images": "portfolio/images/45_LinhPh-7623_story_3.jpg", "description": null, "ordering": 45, "category": 3}}, {"model": "portfolio.photo", "pk": 95, "fields": {"title": "46_LinhPh-8511_story_3.jpg", "images": "portfolio/images/46_LinhPh-8511_story_3.jpg", "description": null, "ordering": 46, "category": 3}}, {"model": "portfolio.photo", "pk": 96, "fields": {"title": "47_LinhPh-8520_story_3.jpg", "images": "portfolio/images/47_LinhPh-8520_story_3.jpg", "description": null, "ordering": 47, "category": 3}}, {"model": "portfolio.photo", "pk": 97, "fields": {"title": "48_LinhPh-7873_story_3.jpg", "images": "portfolio/images/48_LinhPh-7873_story_3.jpg", "description": null, "ordering": 48, "category": 3}}, {"model": "portfolio.photo", "pk": 98, "fields": {"title": "49_LinhPh-8032_story_3.jpg", "images": "portfolio/images/49_LinhPh-8032_story_3.jpg", "description": null, "ordering": 49, "category": 3}}, {"model": "portfolio.photo", "pk": 99, "fields": {"title": "50_LinhPh-8541_story_3.jpg", "images": "portfolio/images/50_LinhPh-8541_story_3.jpg", "description": null, "ordering": 50, "category": 3}}, {"model": "portfolio.photo", "pk": 100, "fields": {"title": "51_LinhPh-8568_story_3.jpg", "images": "portfolio/images/51_LinhPh-8568_story_3.jpg", "description": null, "ordering": 51, "category": 3}}, {"model": "portfolio.photo", "pk": 101, "fields": {"title": "52_LinhPh-8284_story_3.jpg", "images": "portfolio/images/52_LinhPh-8284_story_3.jpg", "description": null, "ordering": 52, "category": 3}}, {"model": "portfolio.photo", "pk": 102, "fields": {"title": "53_LinhPh-8394_story_3.jpg", "images": "portfolio/images/53_LinhPh-8394_story_3.jpg", "description": null, "ordering": 53, "category": 3}}, {"model": "portfolio.photo", "pk": 103, "fields": {"title": "54_LinhPh-8611_story_3.jpg", "images": "portfolio/images/54_LinhPh-8611_story_3.jpg", "description": null, "ordering": 54, "category": 3}}, {"model": "portfolio.photo", "pk": 104, "fields": {"title": "55_LinhPh-8651_story_3.jpg", "images": "portfolio/images/55_LinhPh-8651_story_3.jpg", "description": null, "ordering": 55, "category": 3}}, {"model": "portfolio.photo", "pk": 105, "fields": {"title": "56_LinhPh-8624_story_3.jpg", "images": "portfolio/images/56_LinhPh-8624_story_3.jpg", "description": null, "ordering": 56, "category": 3}}, {"model": "portfolio.photo", "pk": 106, "fields": {"title": "57_LinhPh-9812_story_3.jpg", "images": "portfolio/images/57_LinhPh-9812_story_3.jpg", "description": null, "ordering": 57, "category": 3}}, {"model": "portfolio.photo", "pk": 107, "fields": {"title": "58_LinhPh-8673_story_3.jpg", "images": "portfolio/images/58_LinhPh-8673_story_3.jpg", "description": null, "ordering": 58, "category": 3}}, {"model": "portfolio.photo", "pk": 108, "fields": {"title": "59_LinhPh-8688_story_3.jpg", "images": "portfolio/images/59_LinhPh-8688_story_3.jpg", "description": null, "ordering": 59, "category": 3}}, {"model": "portfolio.photo", "pk": 109, "fields": {"title": "60_LinhPh-9830_story_3.jpg", "images": "portfolio/images/60_LinhPh-9830_story_3.jpg", "description": null, "ordering": 60, "category": 3}}, {"model": "portfolio.photo", "pk": 110, "fields": {"title": "61_LinhPh-9911_story_3.jpg", "images": "portfolio/images/61_LinhPh-9911_story_3.jpg", "description": null, "ordering": 61, "category": 3}}, {"model": "portfolio.photo", "pk": 111, "fields": {"title": "62_PHG_7540_story_3.jpg", "images": "portfolio/images/62_PHG_7540_story_3.jpg", "description": null, "ordering": 62, "category": 3}}, {"model": "portfolio.photo", "pk": 112, "fields": {"title": "63_PHG_8016-3_story_3.jpg", "images": "portfolio/images/63_PHG_8016-3_story_3.jpg", "description": null, "ordering": 63, "category": 3}}, {"model": "portfolio.photo", "pk": 113, "fields": {"title": "64_LinhPh-9933_story_3.jpg", "images": "portfolio/images/64_LinhPh-9933_story_3.jpg", "description": null, "ordering": 64, "category": 3}}, {"model": "portfolio.photo", "pk": 114, "fields": {"title": "65_PHG_5606_story_3.jpg", "images": "portfolio/images/65_PHG_5606_story_3.jpg", "description": null, "ordering": 65, "category": 3}}, {"model": "portfolio.photo", "pk": 115, "fields": {"title": "66_PHG_9155-3_story_3.jpg", "images": "portfolio/images/66_PHG_9155-3_story_3.jpg", "description": null, "ordering": 66, "category": 3}}, {"model": "portfolio.photo", "pk": 116, "fields": {"title": "67_PHG_6822_story_3.jpg", "images": "portfolio/images/67_PHG_6822_story_3.jpg", "description": null, "ordering": 67, "category": 3}}, {"model": "portfolio.photo", "pk": 117, "fields": {"title": "68_PHG_7788_story_3.jpg", "images": "portfolio/images/68_PHG_7788_story_3.jpg", "description": null, "ordering": 68, "category": 3}}, {"model": "portfolio.photo", "pk": 118, "fields": {"title": "69_PHG_7950_story_3.jpg", "images": "portfolio/images/69_PHG_7950_story_3.jpg", "description": null, "ordering": 69, "category": 3}}, {"model": "portfolio.photo", "pk": 119, "fields": {"title": "70_PHG_8814-3_story_3.jpg", "images": "portfolio/images/70_PHG_8814-3_story_3.jpg", "description": null, "ordering": 70, "category": 3}}]